{
  "name": "user",
  "base": "User",
  "idInjection": true,
  "options": {
    "validateUpsert": true
  },
  "properties": {},
  "validations": [],
  "relations":{
    "roles": {
      "type": "hasMany",
      "model": "Role",
      "foreignKey": "role_id"
    }
  },
  "acls": [
    {
      "accessType": "EXECUTE",
      "principalType": "ROLE",
      "principalId": "admin",
      "permission": "ALLOW",
      "property": "find"
    },
    {
      "accessType": "EXECUTE",
      "principalType": "ROLE",
      "principalId": "admin",
      "permission": "ALLOW",
      "property": "getRolesById"
    },
    {
      "accessType": "EXECUTE",
      "principalType": "ROLE",
      "principalId": "$owner",
      "permission": "ALLOW",
      "property": "getRolesById"
    }
  ],
  "methods": {}
}
